{
  "id": "media_text",
  "type": "SharedSlice",
  "name": "MediaText",
  "description": "MediaText",
  "variations": [
    {
      "id": "default",
      "name": "Default",
      "docURL": "...",
      "version": "initial",
      "description": "Default",
      "imageUrl": "",
      "primary": {
        "media": {
          "type": "Link",
          "config": {
            "label": "Media",
            "placeholder": "Alt text",
            "select": "media",
            "allowText": true
          }
        },
        "text_blocks": {
          "type": "Group",
          "config": {
            "label": "Text blocks",
            "repeat": true,
            "fields": {
              "heading": {
                "type": "StructuredText",
                "config": {
                  "label": "Heading",
                  "placeholder": "",
                  "allowTargetBlank": true,
                  "multi": "heading1,heading2,heading3,heading4,heading5,heading6"
                }
              },
              "body": {
                "type": "StructuredText",
                "config": {
                  "label": "Body",
                  "placeholder": "",
                  "allowTargetBlank": true,
                  "multi": "paragraph,hyperlink,list-item"
                }
              }
            }
          }
        }
      },
      "items": {}
    }
  ]
}